odoo/addons/delivery_packaging_archive/README.rst
odoo/addons/delivery_packaging_archive/__init__.py
odoo/addons/delivery_packaging_archive/__manifest__.py
odoo/addons/delivery_packaging_archive/i18n/delivery_packaging_archive.pot
odoo/addons/delivery_packaging_archive/models/__init__.py
odoo/addons/delivery_packaging_archive/models/product_packaging.py
odoo/addons/delivery_packaging_archive/readme/CONTRIBUTORS.rst
odoo/addons/delivery_packaging_archive/readme/DESCRIPTION.rst
odoo/addons/delivery_packaging_archive/static/description/icon.png
odoo/addons/delivery_packaging_archive/static/description/index.html
odoo/addons/delivery_packaging_archive/views/product_packaging_views.xml
odoo14_addon_delivery_packaging_archive-14.0.1.0.1.dist-info/METADATA
odoo14_addon_delivery_packaging_archive-14.0.1.0.1.dist-info/WHEEL
odoo14_addon_delivery_packaging_archive-14.0.1.0.1.dist-info/top_level.txt
odoo14_addon_delivery_packaging_archive-14.0.1.0.1.dist-info/RECORD
